dgc/__init__.py
dgc/data_loader.py
dgc/debug_tools.py
dgc/dgc.py
dgc/draw_samples.py
dgc/extract_feature.py
dgc/likelihoods.py
dgc/run_model.py
dgc/util.py
dgc/vade.py
dgc-0.1.3.dist-info/LICENSE
dgc-0.1.3.dist-info/METADATA
dgc-0.1.3.dist-info/WHEEL
dgc-0.1.3.dist-info/top_level.txt
dgc-0.1.3.dist-info/RECORD
