Metadata-Version: 2.1
Name: dgc
Version: 0.1.3
Summary: An accompanying package for the paper, Deep Goal-Oriented Clustering
Home-page: https://github.com/uncbiag/dgc
Author: Yifeng Shi
Author-email: yifengs@cs.unc.edu
License: UNC
Platform: UNKNOWN
Requires-Python: >=3.7
License-File: LICENSE
Requires-Dist: numpy
Requires-Dist: torch
Requires-Dist: matplotlib
